skyhook_timer/__init__.py
skyhook_timer/admin.py
skyhook_timer/apps.py
skyhook_timer/auth_hooks.py
skyhook_timer/forms.py
skyhook_timer/models.py
skyhook_timer/urls.py
skyhook_timer/views.py
skyhook_timer/migrations/__init__.py
skyhook_timer/templates/skyhook_timer/add_skyhook_timer.html
skyhook_timer/templates/skyhook_timer/view_skyhook_timers.html
skyhook_timer-0.0.49.dist-info/LICENSE
skyhook_timer-0.0.49.dist-info/METADATA
skyhook_timer-0.0.49.dist-info/WHEEL
skyhook_timer-0.0.49.dist-info/top_level.txt
skyhook_timer-0.0.49.dist-info/RECORD
