Metadata-Version: 2.1
Name: skyhook-timer
Version: 0.0.49
Summary: A Skyhook Timer app for Alliance Auth.
Author-email: kjelpw <kjelpw@protonmail.com>
License: Copyright 2024 Kjel Pettenger-Willey
Project-URL: Homepage, https://github.com/kjelpw/skyhook-app
Project-URL: Source, https://github.com/kjelpw/skyhook-app
Keywords: allianceauth,eve-online,skyhook,timers
License-File: LICENSE
Requires-Dist: django>=3.2
